nirodents/__init__.py
nirodents/_version.py
nirodents/interfaces.py
nirodents/viz.py
nirodents/cli/__init__.py
nirodents/cli/brainextraction.py
nirodents/cli/plotmask.py
nirodents/data/artsBrainExtraction_precise_T2w.json
nirodents/data/artsBrainExtraction_testing_T2w.json
nirodents/data/brainextraction_2stage_T1w.json
nirodents/data/brainextraction_2stage_T2w.json
nirodents/data/brainextraction_3stage_T1w.json
nirodents/data/brainextraction_3stage_T2w.json
nirodents/data/brainextraction_precise_T1w.json
nirodents/data/brainextraction_precise_T2w.json
nirodents/utils/__init__.py
nirodents/utils/filtering.py
nirodents/workflows/__init__.py
nirodents/workflows/brainextraction.py
nirodents-0.2.8.dist-info/LICENSE
nirodents-0.2.8.dist-info/METADATA
nirodents-0.2.8.dist-info/WHEEL
nirodents-0.2.8.dist-info/entry_points.txt
nirodents-0.2.8.dist-info/top_level.txt
nirodents-0.2.8.dist-info/RECORD
